{"data":[
{"年份":2020,"企业名称":"互太纺织控股有限公司","边界":"越南","污染物来源":null,"原始污染物名称":"每公吨制成品产生无害废弃物量","污染物":"无害废弃物","分边界污染物物理排放强度":1074.000000000,"分边界污染物物理排放强度单位":"千克/公吨"},
{"年份":2020,"企业名称":"丽新制衣国际有限公司","边界":"香港物业发展","污染物来源":null,"原始污染物名称":"所产生无害废弃物整体密度","污染物":"无害废弃物","分边界污染物物理排放强度":606.710000000,"分边界污染物物理排放强度单位":"千克/平方米"},
{"年份":2020,"企业名称":"丽新发展有限公司","边界":"香港物业发展","污染物来源":null,"原始污染物名称":"所产生无害废弃物密度","污染物":"无害废弃物","分边界污染物物理排放强度":606.710000000,"分边界污染物物理排放强度单位":"千克/平方米"},
{"年份":2020,"企业名称":"互太纺织控股有限公司","边界":"越南","污染物来源":null,"原始污染物名称":"每公吨制成品产生有害废弃物量","污染物":"有害废弃物","分边界污染物物理排放强度":373.000000000,"分边界污染物物理排放强度单位":"千克/公吨"},
{"年份":2020,"企业名称":"融创中国控股有限公司","边界":"地产集团及文化集团","污染物来源":null,"原始污染物名称":"无害废弃物密度","污染物":"无害废弃物","分边界污染物物理排放强度":203.750000000,"分边界污染物物理排放强度单位":"千克/员工总人数"},
{"年份":2020,"企业名称":"力劲科技集团有限公司","边界":"制造铸件","污染物来源":null,"原始污染物名称":"无害固体废物密度","污染物":"无害废弃物","分边界污染物物理排放强度":124.410000000,"分边界污染物物理排放强度单位":"吨/千吨产量"},
{"年份":2020,"企业名称":"丽新发展有限公司","边界":"香港物业投资","污染物来源":null,"原始污染物名称":"所产生无害废弃物密度","污染物":"无害废弃物","分边界污染物物理排放强度":39.870000000,"分边界污染物物理排放强度单位":"千克/平方米"},
{"年份":2020,"企业名称":"信义玻璃控股有限公司","边界":"浮法玻璃","污染物来源":null,"原始污染物名称":"无害废弃物排放密度","污染物":"无害废弃物","分边界污染物物理排放强度":37.960000000,"分边界污染物物理排放强度单位":"公斤/吨"},
{"年份":2020,"企业名称":"丽新制衣国际有限公司","边界":"香港物业投资","污染物来源":null,"原始污染物名称":"所产生无害废弃物密度","污染物":"无害废弃物","分边界污染物物理排放强度":32.840000000,"分边界污染物物理排放强度单位":"千克/平方米"},
{"年份":2020,"企业名称":"丽新制衣国际有限公司","边界":"中国物业投资","污染物来源":null,"原始污染物名称":"所产生无害废弃物密度","污染物":"无害废弃物","分边界污染物物理排放强度":14.890000000,"分边界污染物物理排放强度单位":"千克/平方米"},
{"年份":2020,"企业名称":"丽新发展有限公司","边界":"中国物业投资","污染物来源":null,"原始污染物名称":"所产生无害废弃物密度","污染物":"无害废弃物","分边界污染物物理排放强度":14.890000000,"分边界污染物物理排放强度单位":"千克/平方米"},
{"年份":2020,"企业名称":"互太纺织控股有限公司","边界":"越南","污染物来源":null,"原始污染物名称":"硫氧化物每公吨制成品排放","污染物":"其他","分边界污染物物理排放强度":12.380000000,"分边界污染物物理排放强度单位":"千克/公吨"},
{"年份":2020,"企业名称":"福耀玻璃工业集团股份有限公司","边界":"汽车玻璃","污染物来源":null,"原始污染物名称":"无害废弃物排放密度","污染物":"无害废弃物","分边界污染物物理排放强度":10.400000000,"分边界污染物物理排放强度单位":"吨/万平方米产品"},
{"年份":2020,"企业名称":"福耀玻璃工业集团股份有限公司","边界":"浮法玻璃","污染物来源":null,"原始污染物名称":"无害废弃物排放密度","污染物":"无害废弃物","分边界污染物物理排放强度":10.040000000,"分边界污染物物理排放强度单位":"吨/万平方米产品"},
{"年份":2020,"企业名称":"互太纺织控股有限公司","边界":"番禺","污染物来源":null,"原始污染物名称":"每公吨制成品产生有害废弃物量","污染物":"有害废弃物","分边界污染物物理排放强度":8.730000000,"分边界污染物物理排放强度单位":"千克/公吨"},
{"年份":2020,"企业名称":"丰盛控股有限公司","边界":"教育业务","污染物来源":null,"原始污染物名称":"无害废弃物密度","污染物":"无害废弃物","分边界污染物物理排放强度":7.490000000,"分边界污染物物理排放强度单位":"千克/平方米"},
{"年份":2020,"企业名称":"互太纺织控股有限公司","边界":"越南","污染物来源":null,"原始污染物名称":"氮氧化物每公吨制成品排放","污染物":"氮氧化物","分边界污染物物理排放强度":5.210000000,"分边界污染物物理排放强度单位":"千克/公吨"},
{"年份":2020,"企业名称":"丰盛控股有限公司","边界":"旅游业务","污染物来源":null,"原始污染物名称":"无害废弃物密度","污染物":"无害废弃物","分边界污染物物理排放强度":3.830000000,"分边界污染物物理排放强度单位":"千克/每住客入住晚数"},
{"年份":2020,"企业名称":"丽新制衣国际有限公司","边界":"酒店","污染物来源":null,"原始污染物名称":"所产生无害废弃物整体密度","污染物":"无害废弃物","分边界污染物物理排放强度":3.200000000,"分边界污染物物理排放强度单位":"千克/平方米"},
{"年份":2020,"企业名称":"丽新发展有限公司","边界":"酒店","污染物来源":null,"原始污染物名称":"所产生无害废弃物密度","污染物":"无害废弃物","分边界污染物物理排放强度":3.200000000,"分边界污染物物理排放强度单位":"千克/平方米"},
{"年份":2020,"企业名称":"互太纺织控股有限公司","边界":"越南","污染物来源":null,"原始污染物名称":"颗粒物每公吨制成品排放","污染物":"颗粒物","分边界污染物物理排放强度":2.830000000,"分边界污染物物理排放强度单位":"千克/公吨"},
{"年份":2020,"企业名称":"广州富力地产股份有限公司","边界":"办公场所","污染物来源":null,"原始污染物名称":"无害废弃物产生密度","污染物":"无害废弃物","分边界污染物物理排放强度":2.530000000,"分边界污染物物理排放强度单位":"吨/平方米"},
{"年份":2020,"企业名称":"丽新制衣国际有限公司","边界":"餐饮","污染物来源":null,"原始污染物名称":"所产生无害废弃物密度","污染物":"无害废弃物","分边界污染物物理排放强度":2.190000000,"分边界污染物物理排放强度单位":"千克/平方米"},
{"年份":2020,"企业名称":"丽新发展有限公司","边界":"餐饮","污染物来源":null,"原始污染物名称":"所产生无害废弃物密度","污染物":"无害废弃物","分边界污染物物理排放强度":2.190000000,"分边界污染物物理排放强度单位":"千克/平方米"},
{"年份":2020,"企业名称":"信义玻璃控股有限公司","边界":"汽车玻璃","污染物来源":null,"原始污染物名称":"无害废弃物排放密度","污染物":"无害废弃物","分边界污染物物理排放强度":2.170000000,"分边界污染物物理排放强度单位":"公斤/平方米"},
{"年份":2020,"企业名称":"中骏集团控股有限公司","边界":"总部办公室","污染物来源":null,"原始污染物名称":"有害废弃物密度","污染物":"有害废弃物","分边界污染物物理排放强度":2.110000000,"分边界污染物物理排放强度单位":"公吨/千平方米"},
{"年份":2020,"企业名称":"信义玻璃控股有限公司","边界":"建筑玻璃","污染物来源":null,"原始污染物名称":"无害废弃物排放密度","污染物":"无害废弃物","分边界污染物物理排放强度":1.930000000,"分边界污染物物理排放强度单位":"公斤/平方米"},
{"年份":2020,"企业名称":"丽新制衣国际有限公司","边界":"中国物业发展","污染物来源":null,"原始污染物名称":"所产生无害废弃物整体密度","污染物":"无害废弃物","分边界污染物物理排放强度":1.350000000,"分边界污染物物理排放强度单位":"千克/平方米"},
{"年份":2020,"企业名称":"丽新发展有限公司","边界":"中国物业发展","污染物来源":null,"原始污染物名称":"所产生无害废弃物密度","污染物":"无害废弃物","分边界污染物物理排放强度":1.350000000,"分边界污染物物理排放强度单位":"千克/平方米"},
{"年份":2020,"企业名称":"丽新制衣国际有限公司","边界":"娱乐","污染物来源":null,"原始污染物名称":"所产生无害废弃物整体密度","污染物":"无害废弃物","分边界污染物物理排放强度":1.210000000,"分边界污染物物理排放强度单位":"千克/平方米"},
{"年份":2020,"企业名称":"丽新发展有限公司","边界":"娱乐","污染物来源":null,"原始污染物名称":"所产生无害废弃物密度","污染物":"无害废弃物","分边界污染物物理排放强度":1.210000000,"分边界污染物物理排放强度单位":"千克/平方米"},
{"年份":2020,"企业名称":"复星旅游文化集团","边界":"Club Med","污染物来源":null,"原始污染物名称":"未分拣垃圾密度","污染物":"无害废弃物","分边界污染物物理排放强度":1.209000000,"分边界污染物物理排放强度单位":"千克/总酒店天数"},
{"年份":2020,"企业名称":"复星旅游文化集团","边界":"Club Med","污染物来源":null,"原始污染物名称":"剩余垃圾的平均量","污染物":"无害废弃物","分边界污染物物理排放强度":1.200000000,"分边界污染物物理排放强度单位":"千克/JHT"},
{"年份":2020,"企业名称":"丽新制衣国际有限公司","边界":"剧院","污染物来源":null,"原始污染物名称":"已处理无害废弃物密度","污染物":"无害废弃物","分边界污染物物理排放强度":1.060000000,"分边界污染物物理排放强度单位":"千克/平方米"},
{"年份":2020,"企业名称":"丽新发展有限公司","边界":"剧院","污染物来源":null,"原始污染物名称":"所处理无害废弃物密度","污染物":"无害废弃物","分边界污染物物理排放强度":1.060000000,"分边界污染物物理排放强度单位":"千克/平方米"},
{"年份":2020,"企业名称":"丽新制衣国际有限公司","边界":"中国物业发展","污染物来源":null,"原始污染物名称":"已处理有害废弃物密度","污染物":"有害废弃物","分边界污染物物理排放强度":1.040000000,"分边界污染物物理排放强度单位":"千克/平方米"},
{"年份":2020,"企业名称":"丽新发展有限公司","边界":"中国物业发展","污染物来源":null,"原始污染物名称":"已处理有害废弃物密度","污染物":"有害废弃物","分边界污染物物理排放强度":1.040000000,"分边界污染物物理排放强度单位":"千克/平方米"},
{"年份":2020,"企业名称":"复星旅游文化集团","边界":"Club Med","污染物来源":null,"原始污染物名称":"干垃圾（包装、塑料、金属）密度","污染物":"无害废弃物","分边界污染物物理排放强度":0.900000000,"分边界污染物物理排放强度单位":"千克/总酒店天数"},
{"年份":2020,"企业名称":"远东发展有限公司","边界":"酒店","污染物来源":null,"原始污染物名称":"无害废弃物密度","污染物":"无害废弃物","分边界污染物物理排放强度":0.880000000,"分边界污染物物理排放强度单位":"公吨/千间客房每晚"},
{"年份":2020,"企业名称":"力劲科技集团有限公司","边界":"压铸机","污染物来源":null,"原始污染物名称":"有害固体废物密度","污染物":"有害废弃物","分边界污染物物理排放强度":0.860000000,"分边界污染物物理排放强度单位":"吨/每台"},
{"年份":2020,"企业名称":"丰盛控股有限公司","边界":"旅游业务","污染物来源":null,"原始污染物名称":"有害废弃物密度","污染物":"有害废弃物","分边界污染物物理排放强度":0.830000000,"分边界污染物物理排放强度单位":"千克/每住客入住晚数"},
{"年份":2020,"企业名称":"复星旅游文化集团","边界":"Club Med","污染物来源":null,"原始污染物名称":"纸板密度","污染物":"无害废弃物","分边界污染物物理排放强度":0.768000000,"分边界污染物物理排放强度单位":"千克/总酒店天数"},
{"年份":2020,"企业名称":"互太纺织控股有限公司","边界":"番禺","污染物来源":null,"原始污染物名称":"氮氧化物每公吨制成品排放","污染物":"氮氧化物","分边界污染物物理排放强度":0.700000000,"分边界污染物物理排放强度单位":"千克/公吨"},
{"年份":2020,"企业名称":"远东发展有限公司","边界":"酒店","污染物来源":null,"原始污染物名称":"有害废弃物密度","污染物":"有害废弃物","分边界污染物物理排放强度":0.690000000,"分边界污染物物理排放强度单位":"公吨/百万间客房每晚"},
{"年份":2020,"企业名称":"丰盛控股有限公司","边界":"教育业务","污染物来源":null,"原始污染物名称":"有害废弃物密度","污染物":"有害废弃物","分边界污染物物理排放强度":0.670000000,"分边界污染物物理排放强度单位":"千克/平方米"},
{"年份":2020,"企业名称":"远东发展有限公司","边界":"物业发展","污染物来源":null,"原始污染物名称":"有害废弃物密度","污染物":"有害废弃物","分边界污染物物理排放强度":0.670000000,"分边界污染物物理排放强度单位":"公吨/千平方米"},
{"年份":2020,"企业名称":"复星旅游文化集团","边界":"Club Med","污染物来源":null,"原始污染物名称":"可生物降解的垃圾密度","污染物":"无害废弃物","分边界污染物物理排放强度":0.613000000,"分边界污染物物理排放强度单位":"千克/总酒店天数"},
{"年份":2020,"企业名称":"福耀玻璃工业集团股份有限公司","边界":"浮法玻璃","污染物来源":null,"原始污染物名称":"有害废弃物排放密度","污染物":"有害废弃物","分边界污染物物理排放强度":0.450000000,"分边界污染物物理排放强度单位":"吨/万平方米产品"},
{"年份":2020,"企业名称":"广州富力地产股份有限公司","边界":"商业管理","污染物来源":null,"原始污染物名称":"无害废弃物产生密度","污染物":"无害废弃物","分边界污染物物理排放强度":0.419000000,"分边界污染物物理排放强度单位":"吨/平方米"},
{"年份":2020,"企业名称":"复星旅游文化集团","边界":"Club Med","污染物来源":null,"原始污染物名称":"木材密度","污染物":"无害废弃物","分边界污染物物理排放强度":0.371000000,"分边界污染物物理排放强度单位":"千克/总酒店天数"},
{"年份":2020,"企业名称":"复星旅游文化集团","边界":"Club Med","污染物来源":null,"原始污染物名称":"有害废弃物密度","污染物":"有害废弃物","分边界污染物物理排放强度":0.370000000,"分边界污染物物理排放强度单位":"千克/总酒店天数"},
{"年份":2020,"企业名称":"复星旅游文化集团","边界":"Club Med","污染物来源":null,"原始污染物名称":"纸张密度","污染物":"无害废弃物","分边界污染物物理排放强度":0.298000000,"分边界污染物物理排放强度单位":"千克/总酒店天数"},
{"年份":2020,"企业名称":"第一创业证券股份有限公司","边界":"总部","污染物来源":null,"原始污染物名称":"人均废物产生量","污染物":"其他","分边界污染物物理排放强度":0.290000000,"分边界污染物物理排放强度单位":"吨/人"},
{"年份":2020,"企业名称":"旭辉控股(集团)有限公司","边界":"在建工程","污染物来源":null,"原始污染物名称":"所产生无害废弃物密度","污染物":"无害废弃物","分边界污染物物理排放强度":0.280000000,"分边界污染物物理排放强度单位":"吨/平方米建筑面积"},
{"年份":2020,"企业名称":"小米集团","边界":"中国大陆主要办公区域","污染物来源":null,"原始污染物名称":"人均无害废弃物","污染物":"无害废弃物","分边界污染物物理排放强度":0.240000000,"分边界污染物物理排放强度单位":"吨/人"},
{"年份":2020,"企业名称":"尖沙咀置业集团有限公司","边界":"建筑工地","污染物来源":null,"原始污染物名称":"无害废弃物密度","污染物":"无害废弃物","分边界污染物物理排放强度":0.240000000,"分边界污染物物理排放强度单位":"公吨/平方米"},
{"年份":2020,"企业名称":"创维集团有限公司(开曼)","边界":"电视业务","污染物来源":null,"原始污染物名称":"无害废弃物强度","污染物":"无害废弃物","分边界污染物物理排放强度":0.200000000,"分边界污染物物理排放强度单位":"吨/每千个生产产品单位"},
{"年份":2020,"企业名称":"广州富力地产股份有限公司","边界":"酒店","污染物来源":null,"原始污染物名称":"无害废弃物产生密度","污染物":"无害废弃物","分边界污染物物理排放强度":0.180000000,"分边界污染物物理排放强度单位":"吨/平方米"},
{"年份":2020,"企业名称":"复星旅游文化集团","边界":"Club Med","污染物来源":null,"原始污染物名称":"玻璃密度","污染物":"无害废弃物","分边界污染物物理排放强度":0.163000000,"分边界污染物物理排放强度单位":"千克/总酒店天数"},
{"年份":2020,"企业名称":"力劲科技集团有限公司","边界":"注塑机","污染物来源":null,"原始污染物名称":"无害固体废物密度","污染物":"无害废弃物","分边界污染物物理排放强度":0.160000000,"分边界污染物物理排放强度单位":"吨/每台"},
{"年份":2020,"企业名称":"福耀玻璃工业集团股份有限公司","边界":"汽车玻璃","污染物来源":null,"原始污染物名称":"有害废弃物排放密度","污染物":"有害废弃物","分边界污染物物理排放强度":0.140000000,"分边界污染物物理排放强度单位":"吨/万平方米产品"},
{"年份":2020,"企业名称":"互太纺织控股有限公司","边界":"番禺","污染物来源":null,"原始污染物名称":"硫氧化物每公吨制成品排放","污染物":"其他","分边界污染物物理排放强度":0.140000000,"分边界污染物物理排放强度单位":"千克/公吨"},
{"年份":2020,"企业名称":"互太纺织控股有限公司","边界":"番禺","污染物来源":null,"原始污染物名称":"颗粒物每公吨制成品排放","污染物":"颗粒物","分边界污染物物理排放强度":0.130000000,"分边界污染物物理排放强度单位":"千克/公吨"},
{"年份":2020,"企业名称":"丰盛控股有限公司","边界":"南京总部及香港办公室","污染物来源":null,"原始污染物名称":"无害废弃物密度","污染物":"无害废弃物","分边界污染物物理排放强度":0.120000000,"分边界污染物物理排放强度单位":"公吨/人"},
{"年份":2020,"企业名称":"广州富力地产股份有限公司","边界":"在建项目","污染物来源":null,"原始污染物名称":"无害废弃物产生密度","污染物":"无害废弃物","分边界污染物物理排放强度":0.113000000,"分边界污染物物理排放强度单位":"吨/平方米"},
{"年份":2020,"企业名称":"信义玻璃控股有限公司","边界":"浮法玻璃","污染物来源":null,"原始污染物名称":"有害废弃物排放密度","污染物":"有害废弃物","分边界污染物物理排放强度":0.110000000,"分边界污染物物理排放强度单位":"公斤/吨"},
{"年份":2020,"企业名称":"融创中国控股有限公司","边界":"服务集团","污染物来源":null,"原始污染物名称":"无害废弃物密度","污染物":"无害废弃物","分边界污染物物理排放强度":0.100000000,"分边界污染物物理排放强度单位":"千克/平方米"},
{"年份":2020,"企业名称":"美团","边界":"总部属性职场","污染物来源":null,"原始污染物名称":"人均无害废弃物","污染物":"无害废弃物","分边界污染物物理排放强度":0.080000000,"分边界污染物物理排放强度单位":"吨/雇员"},
{"年份":2020,"企业名称":"美团","边界":"区域销售职场","污染物来源":null,"原始污染物名称":"人均无害废弃物","污染物":"无害废弃物","分边界污染物物理排放强度":0.080000000,"分边界污染物物理排放强度单位":"吨/雇员"},
{"年份":2020,"企业名称":"信和置业有限公司","边界":"总部","污染物来源":null,"原始污染物名称":"有害废弃物密度","污染物":"有害废弃物","分边界污染物物理排放强度":0.080000000,"分边界污染物物理排放强度单位":"公斤/员工"},
{"年份":2020,"企业名称":"信和置业有限公司","边界":"建筑工地","污染物来源":null,"原始污染物名称":"无害废弃物密度","污染物":"无害废弃物","分边界污染物物理排放强度":0.067000000,"分边界污染物物理排放强度单位":"公吨/平方米"},
{"年份":2020,"企业名称":"尖沙咀置业集团有限公司","边界":"总部","污染物来源":null,"原始污染物名称":"有害废弃物密度","污染物":"有害废弃物","分边界污染物物理排放强度":0.060000000,"分边界污染物物理排放强度单位":"公斤/员工"},
{"年份":2020,"企业名称":"力劲科技集团有限公司","边界":"电脑数控加工中心","污染物来源":null,"原始污染物名称":"有害固体废物密度","污染物":"有害废弃物","分边界污染物物理排放强度":0.060000000,"分边界污染物物理排放强度单位":"吨/每台"},
{"年份":2020,"企业名称":"中骏集团控股有限公司","边界":"在建项目","污染物来源":null,"原始污染物名称":"有害废弃物密度","污染物":"有害废弃物","分边界污染物物理排放强度":0.040000000,"分边界污染物物理排放强度单位":"公吨/千平方米"},
{"年份":2020,"企业名称":"中国飞机租赁集团控股有限公司","边界":"香港总部","污染物来源":null,"原始污染物名称":"无害废弃物密度","污染物":"无害废弃物","分边界污染物物理排放强度":0.030000000,"分边界污染物物理排放强度单位":"吨/雇员"},
{"年份":2020,"企业名称":"中国飞机租赁集团控股有限公司","边界":"中国内地办事处","污染物来源":null,"原始污染物名称":"无害废弃物密度","污染物":"无害废弃物","分边界污染物物理排放强度":0.030000000,"分边界污染物物理排放强度单位":"吨/雇员"},
{"年份":2020,"企业名称":"信义玻璃控股有限公司","边界":"汽车玻璃","污染物来源":null,"原始污染物名称":"有害废弃物排放密度","污染物":"有害废弃物","分边界污染物物理排放强度":0.020000000,"分边界污染物物理排放强度单位":"公斤/平方米"},
{"年份":2020,"企业名称":"远东发展有限公司","边界":"物业发展","污染物来源":null,"原始污染物名称":"无害废弃物密度","污染物":"无害废弃物","分边界污染物物理排放强度":0.020000000,"分边界污染物物理排放强度单位":"公吨/平方米"},
{"年份":2020,"企业名称":"尖沙咀置业集团有限公司","边界":"总部","污染物来源":null,"原始污染物名称":"无害废弃物密度","污染物":"无害废弃物","分边界污染物物理排放强度":0.020000000,"分边界污染物物理排放强度单位":"公吨/员工"},
{"年份":2020,"企业名称":"信和置业有限公司","边界":"总部","污染物来源":null,"原始污染物名称":"无害废弃物密度","污染物":"无害废弃物","分边界污染物物理排放强度":0.020000000,"分边界污染物物理排放强度单位":"公吨/员工"},
{"年份":2020,"企业名称":"小米集团","边界":"中国大陆主要办公区域","污染物来源":null,"原始污染物名称":"人均有害废弃物","污染物":"有害废弃物","分边界污染物物理排放强度":0.019000000,"分边界污染物物理排放强度单位":"千克/人"},
{"年份":2020,"企业名称":"广州富力地产股份有限公司","边界":"酒店","污染物来源":null,"原始污染物名称":"危险废弃物产生密度","污染物":"有害废弃物","分边界污染物物理排放强度":0.011000000,"分边界污染物物理排放强度单位":"公斤/平方米"},
{"年份":2020,"企业名称":"尖沙咀置业集团有限公司","边界":"酒店","污染物来源":null,"原始污染物名称":"无害废弃物密度","污染物":"无害废弃物","分边界污染物物理排放强度":0.010000000,"分边界污染物物理排放强度单位":"公吨/住客晚数"},
{"年份":2020,"企业名称":"信和置业有限公司","边界":"酒店","污染物来源":null,"原始污染物名称":"无害废弃物密度","污染物":"无害废弃物","分边界污染物物理排放强度":0.010000000,"分边界污染物物理排放强度单位":"公吨/住客晚数"},
{"年份":2020,"企业名称":"复星旅游文化集团","边界":"Club Med","污染物来源":null,"原始污染物名称":"陶瓷密度","污染物":"无害废弃物","分边界污染物物理排放强度":0.007000000,"分边界污染物物理排放强度单位":"千克/总酒店天数"},
{"年份":2020,"企业名称":"万科企业股份有限公司","边界":"地产系统","污染物来源":null,"原始污染物名称":"有害废弃物密度","污染物":"有害废弃物","分边界污染物物理排放强度":0.005600000,"分边界污染物物理排放强度单位":"千克/平方米"},
{"年份":2020,"企业名称":"创维集团有限公司(开曼)","边界":"电视业务","污染物来源":null,"原始污染物名称":"有害废弃物强度","污染物":"有害废弃物","分边界污染物物理排放强度":0.005000000,"分边界污染物物理排放强度单位":"吨/每千个生产产品单位"},
{"年份":2020,"企业名称":"通用环球医疗集团有限公司","边界":"医院集团业务","污染物来源":null,"原始污染物名称":"医疗废弃物产生密度","污染物":"有害废弃物","分边界污染物物理排放强度":0.005000000,"分边界污染物物理排放强度单位":"吨/平方米面积"},
{"年份":2020,"企业名称":"万科企业股份有限公司","边界":"地产系统","污染物来源":null,"原始污染物名称":"无害废弃物密度","污染物":"无害废弃物","分边界污染物物理排放强度":0.004500000,"分边界污染物物理排放强度单位":"千克/平方米"},
{"年份":2020,"企业名称":"丽新制衣国际有限公司","边界":"剧院","污染物来源":null,"原始污染物名称":"已处理有害废弃物密度","污染物":"有害废弃物","分边界污染物物理排放强度":0.004400000,"分边界污染物物理排放强度单位":"千克/平方米"},
{"年份":2020,"企业名称":"万科企业股份有限公司","边界":"物业系统","污染物来源":null,"原始污染物名称":"有害废弃物密度","污染物":"有害废弃物","分边界污染物物理排放强度":0.004000000,"分边界污染物物理排放强度单位":"千克/平方米"},
{"年份":2020,"企业名称":"旭辉控股(集团)有限公司","边界":"行政办公","污染物来源":null,"原始污染物名称":"所产生无害废弃物密度","污染物":"无害废弃物","分边界污染物物理排放强度":0.004000000,"分边界污染物物理排放强度单位":"吨/平方米建筑面积"},
{"年份":2020,"企业名称":"丽新制衣国际有限公司","边界":"酒店","污染物来源":null,"原始污染物名称":"已处理有害废弃物整体密度","污染物":"有害废弃物","分边界污染物物理排放强度":0.004000000,"分边界污染物物理排放强度单位":"千克/平方米"},
{"年份":2020,"企业名称":"丽新发展有限公司","边界":"酒店","污染物来源":null,"原始污染物名称":"已处理有害废弃物密度","污染物":"有害废弃物","分边界污染物物理排放强度":0.004000000,"分边界污染物物理排放强度单位":"千克/平方米"},
{"年份":2020,"企业名称":"丽新发展有限公司","边界":"剧院","污染物来源":null,"原始污染物名称":"已处理有害废弃物密度","污染物":"有害废弃物","分边界污染物物理排放强度":0.004000000,"分边界污染物物理排放强度单位":"千克/平方米"},
{"年份":2020,"企业名称":"万科企业股份有限公司","边界":"物业系统","污染物来源":null,"原始污染物名称":"无害废弃物密度","污染物":"无害废弃物","分边界污染物物理排放强度":0.003600000,"分边界污染物物理排放强度单位":"千克/平方米"},
{"年份":2020,"企业名称":"旭辉控股(集团)有限公司","边界":"商业运营","污染物来源":null,"原始污染物名称":"所产生无害废弃物密度","污染物":"无害废弃物","分边界污染物物理排放强度":0.003000000,"分边界污染物物理排放强度单位":"吨/平方米建筑面积"},
{"年份":2020,"企业名称":"丽新发展有限公司","边界":"香港物业投资","污染物来源":null,"原始污染物名称":"已处理有害废弃物密度","污染物":"有害废弃物","分边界污染物物理排放强度":0.002600000,"分边界污染物物理排放强度单位":"千克/平方米"},
{"年份":2020,"企业名称":"丽新制衣国际有限公司","边界":"香港物业投资","污染物来源":null,"原始污染物名称":"已处理有害废弃物密度","污染物":"有害废弃物","分边界污染物物理排放强度":0.002400000,"分边界污染物物理排放强度单位":"千克/平方米"},
{"年份":2020,"企业名称":"广州富力地产股份有限公司","边界":"商业管理","污染物来源":null,"原始污染物名称":"危险废弃物产生密度","污染物":"有害废弃物","分边界污染物物理排放强度":0.002000000,"分边界污染物物理排放强度单位":"公斤/平方米"},
{"年份":2020,"企业名称":"中骏集团控股有限公司","边界":"在建项目","污染物来源":null,"原始污染物名称":"有害废弃物密度","污染物":"有害废弃物","分边界污染物物理排放强度":0.002000000,"分边界污染物物理排放强度单位":"千克/千平方米"},
{"年份":2020,"企业名称":"信利国际有限公司","边界":"中国","污染物来源":null,"原始污染物名称":"有害废弃物密度","污染物":"有害废弃物","分边界污染物物理排放强度":0.002000000,"分边界污染物物理排放强度单位":"吨/平方米"},
{"年份":2020,"企业名称":"联想控股股份有限公司","边界":"卢森堡国际银行总部","污染物来源":null,"原始污染物名称":"氮氧化物(NOx)","污染物":"氮氧化物","分边界污染物物理排放强度":0.001440000,"分边界污染物物理排放强度单位":"千克/平方米"},
{"年份":2020,"企业名称":"中国海外宏洋集团有限公司","边界":"中国内地","污染物来源":null,"原始污染物名称":"无害废弃物密度","污染物":"无害废弃物","分边界污染物物理排放强度":0.001100000,"分边界污染物物理排放强度单位":"吨/员工"},
{"年份":2020,"企业名称":"信利国际有限公司","边界":"香港","污染物来源":null,"原始污染物名称":"无害废弃物密度","污染物":"无害废弃物","分边界污染物物理排放强度":0.001000000,"分边界污染物物理排放强度单位":"吨/平方米"},
{"年份":2020,"企业名称":"信利国际有限公司","边界":"中国","污染物来源":null,"原始污染物名称":"无害废弃物密度","污染物":"无害废弃物","分边界污染物物理排放强度":0.001000000,"分边界污染物物理排放强度单位":"吨/平方米"},
{"年份":2020,"企业名称":"尖沙咀置业集团有限公司","边界":"物业管理","污染物来源":null,"原始污染物名称":"有害废弃物密度","污染物":"有害废弃物","分边界污染物物理排放强度":0.001000000,"分边界污染物物理排放强度单位":"公斤/平方米"},
{"年份":2020,"企业名称":"信和置业有限公司","边界":"物业管理","污染物来源":null,"原始污染物名称":"有害废弃物密度","污染物":"有害废弃物","分边界污染物物理排放强度":0.001000000,"分边界污染物物理排放强度单位":"公斤/平方米"},
{"年份":2020,"企业名称":"丽新制衣国际有限公司","边界":"中国物业投资","污染物来源":null,"原始污染物名称":"已处理有害废弃物密度","污染物":"有害废弃物","分边界污染物物理排放强度":0.000800000,"分边界污染物物理排放强度单位":"千克/平方米"},
{"年份":2020,"企业名称":"丽新发展有限公司","边界":"中国物业投资","污染物来源":null,"原始污染物名称":"已处理有害废弃物密度","污染物":"有害废弃物","分边界污染物物理排放强度":0.000800000,"分边界污染物物理排放强度单位":"千克/平方米"},
{"年份":2020,"企业名称":"纷美包装有限公司","边界":"化妆品零售","污染物来源":null,"原始污染物名称":"每千包无害固体废弃物","污染物":"无害废弃物","分边界污染物物理排放强度":0.000700000,"分边界污染物物理排放强度单位":"吨/千包"},
{"年份":2020,"企业名称":"联想控股股份有限公司","边界":"融科","污染物来源":null,"原始污染物名称":"氮氧化物(NOx)","污染物":"氮氧化物","分边界污染物物理排放强度":0.000379000,"分边界污染物物理排放强度单位":"千克/平方米"},
{"年份":2020,"企业名称":"中国飞机租赁集团控股有限公司","边界":"爱尔兰办事处","污染物来源":null,"原始污染物名称":"无害废弃物密度","污染物":"无害废弃物","分边界污染物物理排放强度":0.000270000,"分边界污染物物理排放强度单位":"吨/雇员"},
{"年份":2020,"企业名称":"旭辉控股(集团)有限公司","边界":"行政办公","污染物来源":null,"原始污染物名称":"所产生有害废弃物密度","污染物":"有害废弃物","分边界污染物物理排放强度":0.000200000,"分边界污染物物理排放强度单位":"吨/平方米建筑面积"},
{"年份":2020,"企业名称":"伟能集团国际控股有限公司","边界":"IBO项目","污染物来源":null,"原始污染物名称":"IBO项目产生的废油强度","污染物":"其他","分边界污染物物理排放强度":0.000190000,"分边界污染物物理排放强度单位":"公升/千瓦时发电量"},
{"年份":2020,"企业名称":"中国海外宏洋集团有限公司","边界":"中国内地","污染物来源":null,"原始污染物名称":"无害废弃物密度","污染物":"无害废弃物","分边界污染物物理排放强度":0.000100000,"分边界污染物物理排放强度单位":"吨/平方米"},
{"年份":2020,"企业名称":"联想控股股份有限公司","边界":"卢森堡国际银行总部","污染物来源":null,"原始污染物名称":"粉尘(PM2.5)","污染物":"颗粒物","分边界污染物物理排放强度":0.000038800,"分边界污染物物理排放强度单位":"千克/平方米"},
{"年份":2020,"企业名称":"联想控股股份有限公司","边界":"融科","污染物来源":null,"原始污染物名称":"粉尘(PM)","污染物":"颗粒物","分边界污染物物理排放强度":0.000024500,"分边界污染物物理排放强度单位":"千克/平方米"},
{"年份":2020,"企业名称":"纷美包装有限公司","边界":"化妆品零售","污染物来源":null,"原始污染物名称":"每千包有害废弃物","污染物":"有害废弃物","分边界污染物物理排放强度":0.000019000,"分边界污染物物理排放强度单位":"吨/千包"},
{"年份":2020,"企业名称":"伟能集团国际控股有限公司","边界":"IBO项目","污染物来源":null,"原始污染物名称":"IBO项目产生的废钢及废铁强度","污染物":"其他","分边界污染物物理排放强度":0.000016000,"分边界污染物物理排放强度单位":"公斤/千瓦时发电量"},
{"年份":2020,"企业名称":"联想控股股份有限公司","边界":"融科","污染物来源":null,"原始污染物名称":"硫氧化物(SOx)","污染物":"其他","分边界污染物物理排放强度":0.000005430,"分边界污染物物理排放强度单位":"千克/平方米"},
{"年份":2020,"企业名称":"联想控股股份有限公司","边界":"卢森堡国际银行总部","污染物来源":null,"原始污染物名称":"硫氧化物(SOx)","污染物":"其他","分边界污染物物理排放强度":0.000003260,"分边界污染物物理排放强度单位":"千克/平方米"},
{"年份":2020,"企业名称":"小米集团","边界":"亦庄智能工厂","污染物来源":null,"原始污染物名称":"人均无害废弃物","污染物":"无害废弃物","分边界污染物物理排放强度":0.190000000,"分边界污染物物理排放强度单位":"吨/人"},
{"年份":2020,"企业名称":"小米集团","边界":"亦庄智能工厂","污染物来源":null,"原始污染物名称":"人均有害废弃物","污染物":"有害废弃物","分边界污染物物理排放强度":0E-9,"分边界污染物物理排放强度单位":"吨/人"},
{"年份":2021,"企业名称":"中国人民保险集团股份有限公司","边界":"集团大楼","污染物来源":null,"原始污染物名称":"一般废弃物","污染物":"无害废弃物","分边界污染物物理排放强度":51.810000000,"分边界污染物物理排放强度单位":"吨/人"},
{"年份":2021,"企业名称":"中国人民保险集团股份有限公司","边界":"集团大楼","污染物来源":null,"原始污染物名称":"危险废弃物","污染物":"有害废弃物","分边界污染物物理排放强度":0.020000000,"分边界污染物物理排放强度单位":"吨/人"},
{"年份":2021,"企业名称":"万科企业股份有限公司","边界":"房地产开发","污染物来源":null,"原始污染物名称":"有害废弃物密度","污染物":"有害废弃物","分边界污染物物理排放强度":0.330000000,"分边界污染物物理排放强度单位":"千克/建筑面积"},
{"年份":2021,"企业名称":"万科企业股份有限公司","边界":"物业","污染物来源":null,"原始污染物名称":"有害废弃物密度","污染物":"有害废弃物","分边界污染物物理排放强度":0.030000000,"分边界污染物物理排放强度单位":"千克/建筑面积"},
{"年份":2021,"企业名称":"万科企业股份有限公司","边界":"酒店与度假","污染物来源":null,"原始污染物名称":"有害废弃物密度","污染物":"有害废弃物","分边界污染物物理排放强度":0.230000000,"分边界污染物物理排放强度单位":"千克/宾客入住房晚"},
{"年份":2021,"企业名称":"万科企业股份有限公司","边界":"总部和公摊公用(印力商业)","污染物来源":null,"原始污染物名称":"有害废弃物密度","污染物":"有害废弃物","分边界污染物物理排放强度":1.100000000,"分边界污染物物理排放强度单位":"千克/建筑面积"},
{"年份":2021,"企业名称":"万科企业股份有限公司","边界":"房地产开发","污染物来源":null,"原始污染物名称":"无害废弃物密度","污染物":"无害废弃物","分边界污染物物理排放强度":0.490000000,"分边界污染物物理排放强度单位":"吨/建筑面积"},
{"年份":2021,"企业名称":"万科企业股份有限公司","边界":"物业","污染物来源":null,"原始污染物名称":"无害废弃物密度","污染物":"无害废弃物","分边界污染物物理排放强度":0.010000000,"分边界污染物物理排放强度单位":"吨/建筑面积"},
{"年份":2021,"企业名称":"万科企业股份有限公司","边界":"酒店与度假","污染物来源":null,"原始污染物名称":"无害废弃物密度","污染物":"无害废弃物","分边界污染物物理排放强度":0.050000000,"分边界污染物物理排放强度单位":"吨/宾客入住房晚"},
{"年份":2021,"企业名称":"万科企业股份有限公司","边界":"高标园区(物流)","污染物来源":null,"原始污染物名称":"无害废弃物密度","污染物":"无害废弃物","分边界污染物物理排放强度":0.004000000,"分边界污染物物理排放强度单位":"吨/建筑面积"},
{"年份":2021,"企业名称":"万科企业股份有限公司","边界":"冷链园区及办公(包含运输)(物流)","污染物来源":null,"原始污染物名称":"无害废弃物密度","污染物":"无害废弃物","分边界污染物物理排放强度":0.020000000,"分边界污染物物理排放强度单位":"吨/建筑面积"},
{"年份":2021,"企业名称":"万科企业股份有限公司","边界":"总部和公摊公用(印力商业)","污染物来源":null,"原始污染物名称":"无害废弃物密度","污染物":"无害废弃物","分边界污染物物理排放强度":0.060000000,"分边界污染物物理排放强度单位":"吨/建筑面积"},
{"年份":2021,"企业名称":"万科企业股份有限公司","边界":"租户使用(印力商业)","污染物来源":null,"原始污染物名称":"无害废弃物密度","污染物":"无害废弃物","分边界污染物物理排放强度":0.020000000,"分边界污染物物理排放强度单位":"吨/建筑面积"},
{"年份":2021,"企业名称":"联想控股股份有限公司","边界":"融科","污染物来源":null,"原始污染物名称":"氮氧化物","污染物":"氮氧化物","分边界污染物物理排放强度":0.370000000,"分边界污染物物理排放强度单位":"千克/平方米"},
{"年份":2021,"企业名称":"联想控股股份有限公司","边界":"融科","污染物来源":null,"原始污染物名称":"硫氧化物","污染物":"二氧化硫","分边界污染物物理排放强度":0.002200000,"分边界污染物物理排放强度单位":"千克/平方米"},
{"年份":2021,"企业名称":"联想控股股份有限公司","边界":"融科","污染物来源":null,"原始污染物名称":"粉尘(PM)","污染物":"颗粒物","分边界污染物物理排放强度":0.030000000,"分边界污染物物理排放强度单位":"千克/平方米"},
{"年份":2021,"企业名称":"联想控股股份有限公司","边界":"卢森堡国际银行","污染物来源":null,"原始污染物名称":"氮氧化物","污染物":"氮氧化物","分边界污染物物理排放强度":0.000600000,"分边界污染物物理排放强度单位":"千克/平方米"},
{"年份":2021,"企业名称":"联想控股股份有限公司","边界":"卢森堡国际银行","污染物来源":null,"原始污染物名称":"硫氧化物","污染物":"二氧化硫","分边界污染物物理排放强度":0.000002000,"分边界污染物物理排放强度单位":"千克/平方米"},
{"年份":2021,"企业名称":"联想控股股份有限公司","边界":"卢森堡国际银行","污染物来源":null,"原始污染物名称":"粉尘(PM)","污染物":"颗粒物","分边界污染物物理排放强度":0.000010000,"分边界污染物物理排放强度单位":"千克/平方米"},
{"年份":2021,"企业名称":"小米集团","边界":"中国大陆办公区","污染物来源":null,"原始污染物名称":"人均无害废弃物","污染物":"无害废弃物","分边界污染物物理排放强度":0.200000000,"分边界污染物物理排放强度单位":"吨/人"},
{"年份":2021,"企业名称":"小米集团","边界":"亦庄智能工厂","污染物来源":null,"原始污染物名称":"人均无害废弃物","污染物":"无害废弃物","分边界污染物物理排放强度":0.260000000,"分边界污染物物理排放强度单位":"吨/人"},
{"年份":2021,"企业名称":"融创中国控股有限公司","边界":"地产及文化集团","污染物来源":null,"原始污染物名称":"无害废弃物密度","污染物":"无害废弃物","分边界污染物物理排放强度":248.210000000,"分边界污染物物理排放强度单位":"千克/人"},
{"年份":2021,"企业名称":"融创中国控股有限公司","边界":"服务集团","污染物来源":null,"原始污染物名称":"无害废弃物密度","污染物":"无害废弃物","分边界污染物物理排放强度":0.030000000,"分边界污染物物理排放强度单位":"千克/平方米"},
{"年份":2021,"企业名称":"融创中国控股有限公司","边界":"文旅集团","污染物来源":null,"原始污染物名称":"无害废弃物密度","污染物":"无害废弃物","分边界污染物物理排放强度":986.400000000,"分边界污染物物理排放强度单位":"千克/人"},
{"年份":2021,"企业名称":"融创中国控股有限公司","边界":"地产及文化集团","污染物来源":null,"原始污染物名称":"有害废弃物密度","污染物":"有害废弃物","分边界污染物物理排放强度":0.270000000,"分边界污染物物理排放强度单位":"千克/人"},
{"年份":2021,"企业名称":"融创中国控股有限公司","边界":"文旅集团","污染物来源":null,"原始污染物名称":"有害废弃物密度","污染物":"有害废弃物","分边界污染物物理排放强度":2.740000000,"分边界污染物物理排放强度单位":"千克/人"},
{"年份":2021,"企业名称":"交通银行股份有限公司","边界":"总行","污染物来源":null,"原始污染物名称":"有害废弃物排放密度","污染物":"有害废弃物","分边界污染物物理排放强度":0.000040000,"分边界污染物物理排放强度单位":"吨/人"},
{"年份":2021,"企业名称":"交通银行股份有限公司","边界":"总行","污染物来源":null,"原始污染物名称":"无害废弃物排放密度","污染物":"无害废弃物","分边界污染物物理排放强度":0.260000000,"分边界污染物物理排放强度单位":"吨/人"},
{"年份":2021,"企业名称":"中升集团控股有限公司","边界":"各经销店","污染物来源":null,"原始污染物名称":"有害废弃物总量","污染物":"有害废弃物","分边界污染物物理排放强度":22.560000000,"分边界污染物物理排放强度单位":"吨/店"},
{"年份":2021,"企业名称":"中升集团控股有限公司","边界":"各经销店","污染物来源":null,"原始污染物名称":"无害废弃物总量","污染物":"无害废弃物","分边界污染物物理排放强度":13.600000000,"分边界污染物物理排放强度单位":"吨/店"},
{"年份":2021,"企业名称":"美团","边界":"总部属性职场","污染物来源":null,"原始污染物名称":"人均有害废弃物","污染物":"有害废弃物","分边界污染物物理排放强度":0.000003000,"分边界污染物物理排放强度单位":"吨/人"},
{"年份":2021,"企业名称":"美团","边界":"总部属性职场","污染物来源":null,"原始污染物名称":"人均无害废弃物","污染物":"无害废弃物","分边界污染物物理排放强度":0.090000000,"分边界污染物物理排放强度单位":"吨/人"},
{"年份":2021,"企业名称":"美团","边界":"区域销售职场","污染物来源":null,"原始污染物名称":"人均有害废弃物","污染物":"有害废弃物","分边界污染物物理排放强度":0.000100000,"分边界污染物物理排放强度单位":"吨/人"},
{"年份":2021,"企业名称":"美团","边界":"区域销售职场","污染物来源":null,"原始污染物名称":"人均无害废弃物","污染物":"无害废弃物","分边界污染物物理排放强度":0.080000000,"分边界污染物物理排放强度单位":"吨/人"},
{"年份":2021,"企业名称":"卓尔智联集团有限公司","边界":"集团办公室","污染物来源":null,"原始污染物名称":"无害废弃物密度","污染物":"无害废弃物","分边界污染物物理排放强度":6.360000000,"分边界污染物物理排放强度单位":"公斤/人"},
{"年份":2021,"企业名称":"旭辉控股(集团)有限公司","边界":"行政办公","污染物来源":null,"原始污染物名称":"有害废弃物密度行政办公","污染物":"有害废弃物","分边界污染物物理排放强度":0.100000000,"分边界污染物物理排放强度单位":"千克/平方米建筑面积"},
{"年份":2021,"企业名称":"旭辉控股(集团)有限公司","边界":"行政办公","污染物来源":null,"原始污染物名称":"无害废弃物密度行政办公","污染物":"无害废弃物","分边界污染物物理排放强度":0.003000000,"分边界污染物物理排放强度单位":"吨/平方米"},
{"年份":2021,"企业名称":"旭辉控股(集团)有限公司","边界":"在建工程","污染物来源":null,"原始污染物名称":"无害废弃物密度在建工程","污染物":"无害废弃物","分边界污染物物理排放强度":0.580000000,"分边界污染物物理排放强度单位":"吨/平方米"},
{"年份":2021,"企业名称":"旭辉控股(集团)有限公司","边界":"商业运营","污染物来源":null,"原始污染物名称":"无害废弃物密度商业运营","污染物":"无害废弃物","分边界污染物物理排放强度":0.020000000,"分边界污染物物理排放强度单位":"吨/平方米"},
{"年份":2021,"企业名称":"英国保诚有限公司","边界":"保诚集团，不包括Jackson","污染物来源":null,"原始污染物名称":"所产生无害废料总量","污染物":"无害废弃物","分边界污染物物理排放强度":0.020000000,"分边界污染物物理排放强度单位":"吨/人"},
{"年份":2021,"企业名称":"国泰航空有限公司","边界":"飞机运作","污染物来源":null,"原始污染物名称":"平均氮氧化物排放/每降落起飞周期(LTO)","污染物":"氮氧化物","分边界污染物物理排放强度":45.000000000,"分边界污染物物理排放强度单位":"公斤/LTO"},
{"年份":2021,"企业名称":"CWT International Limited","边界":"物流业务","污染物来源":null,"原始污染物名称":"无害废弃物产生密度","污染物":"无害废弃物","分边界污染物物理排放强度":0.010000000,"分边界污染物物理排放强度单位":"吨/平方米"},
{"年份":2021,"企业名称":"CWT International Limited","边界":"商品贸易业务","污染物来源":null,"原始污染物名称":"无害废弃物产生密度","污染物":"无害废弃物","分边界污染物物理排放强度":0.003000000,"分边界污染物物理排放强度单位":"吨/平方米"},
{"年份":2021,"企业名称":"中国海外宏洋集团有限公司","边界":"中国内地","污染物来源":null,"原始污染物名称":"有害废弃物密度","污染物":"有害废弃物","分边界污染物物理排放强度":0.030000000,"分边界污染物物理排放强度单位":"吨/千平方米"},
{"年份":2021,"企业名称":"中国海外宏洋集团有限公司","边界":"中国内地","污染物来源":null,"原始污染物名称":"无害废弃物密度","污染物":"无害废弃物","分边界污染物物理排放强度":4.380000000,"分边界污染物物理排放强度单位":"吨/千平方米"},
{"年份":2021,"企业名称":"中国海外宏洋集团有限公司","边界":"香港","污染物来源":null,"原始污染物名称":"有害废弃物密度","污染物":"有害废弃物","分边界污染物物理排放强度":0.004000000,"分边界污染物物理排放强度单位":"吨/千平方米"},
{"年份":2021,"企业名称":"中国海外宏洋集团有限公司","边界":"香港","污染物来源":null,"原始污染物名称":"无害废弃物密度","污染物":"无害废弃物","分边界污染物物理排放强度":1.300000000,"分边界污染物物理排放强度单位":"吨/千平方米"},
{"年份":2021,"企业名称":"香港中华煤气有限公司","边界":"香港","污染物来源":null,"原始污染物名称":"化学废料","污染物":"有害废弃物","分边界污染物物理排放强度":1.800000000,"分边界污染物物理排放强度单位":"公斤/每百万兆焦耳煤气"},
{"年份":2021,"企业名称":"创维集团有限公司(开曼)","边界":"电视业务","污染物来源":null,"原始污染物名称":"无害废弃物强度","污染物":"无害废弃物","分边界污染物物理排放强度":0.010000000,"分边界污染物物理排放强度单位":"吨/每千个生产产品单位"},
{"年份":2021,"企业名称":"创维集团有限公司(开曼)","边界":"电视业务","污染物来源":null,"原始污染物名称":"有害废弃物强度","污染物":"有害废弃物","分边界污染物物理排放强度":0.004000000,"分边界污染物物理排放强度单位":"吨/每千个生产产品单位"},
{"年份":2021,"企业名称":"创维集团有限公司(开曼)","边界":"数字机顶盒业务","污染物来源":null,"原始污染物名称":"无害废弃物强度","污染物":"无害废弃物","分边界污染物物理排放强度":0.000100000,"分边界污染物物理排放强度单位":"吨/每千个生产产品单位"},
{"年份":2021,"企业名称":"创维集团有限公司(开曼)","边界":"数字机顶盒业务","污染物来源":null,"原始污染物名称":"有害废弃物强度","污染物":"有害废弃物","分边界污染物物理排放强度":0.000100000,"分边界污染物物理排放强度单位":"吨/每千个生产产品单位"},
{"年份":2021,"企业名称":"德信中国控股有限公司","边界":"杭州总部","污染物来源":null,"原始污染物名称":"无害废弃物排放密度","污染物":"无害废弃物","分边界污染物物理排放强度":3.010000000,"分边界污染物物理排放强度单位":"千克/平方米"},
{"年份":2021,"企业名称":"德信中国控股有限公司","边界":"项目公司","污染物来源":null,"原始污染物名称":"无害废弃物排放密度","污染物":"无害废弃物","分边界污染物物理排放强度":0.960000000,"分边界污染物物理排放强度单位":"千克/平方米"},
{"年份":2021,"企业名称":"德信中国控股有限公司","边界":"项目公司","污染物来源":null,"原始污染物名称":"有害废弃物排放密度","污染物":"有害废弃物","分边界污染物物理排放强度":0.004000000,"分边界污染物物理排放强度单位":"千克/平方米"},
{"年份":2021,"企业名称":"郑州银行股份有限公司","边界":"总行","污染物来源":null,"原始污染物名称":"生活垃圾","污染物":"无害废弃物","分边界污染物物理排放强度":0.080000000,"分边界污染物物理排放强度单位":"吨/人"},
{"年份":2021,"企业名称":"徽商银行股份有限公司","边界":"总行","污染物来源":null,"原始污染物名称":"无害固体废物","污染物":"无害废弃物","分边界污染物物理排放强度":0.010000000,"分边界污染物物理排放强度单位":"吨/人"},
{"年份":2021,"企业名称":"百得利控股有限公司","边界":"北京办事处及12个4S门店","污染物来源":null,"原始污染物名称":"氮氧化物排放密度","污染物":"氮氧化物","分边界污染物物理排放强度":2.490000000,"分边界污染物物理排放强度单位":"克/平方米"},
{"年份":2021,"企业名称":"百得利控股有限公司","边界":"北京办事处及12个4S门店","污染物来源":null,"原始污染物名称":"硫氧化物排放密度","污染物":"二氧化硫","分边界污染物物理排放强度":0.030000000,"分边界污染物物理排放强度单位":"克/平方米"},
{"年份":2021,"企业名称":"百得利控股有限公司","边界":"北京办事处及12个4S门店","污染物来源":null,"原始污染物名称":"颗粒物排放密度","污染物":"颗粒物","分边界污染物物理排放强度":0.090000000,"分边界污染物物理排放强度单位":"克/平方米"},
{"年份":2021,"企业名称":"通用环球医疗集团有限公司","边界":"医院集团业务","污染物来源":null,"原始污染物名称":"医疗废弃物产生密度","污染物":"有害废弃物","分边界污染物物理排放强度":0.010000000,"分边界污染物物理排放强度单位":"吨/平方米"},
{"年份":2021,"企业名称":"通用环球医疗集团有限公司","边界":"医院集团业务","污染物来源":null,"原始污染物名称":"无害废弃物产生密度","污染物":"无害废弃物","分边界污染物物理排放强度":0.250000000,"分边界污染物物理排放强度单位":"吨/平方米"},
{"年份":2021,"企业名称":"通用环球医疗集团有限公司","边界":"北京总部办公室","污染物来源":null,"原始污染物名称":"废电池产生密度","污染物":"有害废弃物","分边界污染物物理排放强度":1.080000000,"分边界污染物物理排放强度单位":"千克/人"},
{"年份":2021,"企业名称":"通用环球医疗集团有限公司","边界":"北京总部办公室","污染物来源":null,"原始污染物名称":"纸张产生密度","污染物":"无害废弃物","分边界污染物物理排放强度":7.310000000,"分边界污染物物理排放强度单位":"千克/人"},
{"年份":2021,"企业名称":"重庆银行股份有限公司","边界":"总部","污染物来源":null,"原始污染物名称":"餐厨垃圾产生密度","污染物":"无害废弃物","分边界污染物物理排放强度":0.004000000,"分边界污染物物理排放强度单位":"吨/人"},
{"年份":2021,"企业名称":"锐信控股有限公司","边界":"集团业务运营总建筑面积","污染物来源":null,"原始污染物名称":"氮氧化物","污染物":"氮氧化物","分边界污染物物理排放强度":6.460000000,"分边界污染物物理排放强度单位":"克/每平方米"},
{"年份":2021,"企业名称":"锐信控股有限公司","边界":"集团业务运营总建筑面积","污染物来源":null,"原始污染物名称":"呼吸悬浮颗粒物","污染物":"悬浮物","分边界污染物物理排放强度":0.540000000,"分边界污染物物理排放强度单位":"克/每平方米"},
{"年份":2021,"企业名称":"锐信控股有限公司","边界":"集团业务运营总建筑面积","污染物来源":null,"原始污染物名称":"硫氧化物","污染物":"二氧化硫","分边界污染物物理排放强度":0.003000000,"分边界污染物物理排放强度单位":"克/每平方米"},
{"年份":2021,"企业名称":"远东发展有限公司","边界":"酒店","污染物来源":null,"原始污染物名称":"有害废弃物密度","污染物":"有害废弃物","分边界污染物物理排放强度":0.690000000,"分边界污染物物理排放强度单位":"吨/百万间客房每晚"},
{"年份":2021,"企业名称":"远东发展有限公司","边界":"物业发展","污染物来源":null,"原始污染物名称":"有害废弃物密度","污染物":"有害废弃物","分边界污染物物理排放强度":0.670000000,"分边界污染物物理排放强度单位":"吨/千平方米"},
{"年份":2021,"企业名称":"远东发展有限公司","边界":"酒店","污染物来源":null,"原始污染物名称":"无害废弃物密度","污染物":"无害废弃物","分边界污染物物理排放强度":0.880000000,"分边界污染物物理排放强度单位":"吨/千间客房每晚"},
{"年份":2021,"企业名称":"远东发展有限公司","边界":"物业发展","污染物来源":null,"原始污染物名称":"无害废弃物密度","污染物":"无害废弃物","分边界污染物物理排放强度":0.020000000,"分边界污染物物理排放强度单位":"吨/平方米"},
{"年份":2021,"企业名称":"尖沙咀置业集团有限公司","边界":"总部","污染物来源":null,"原始污染物名称":"无害废物弃置强度","污染物":"无害废弃物","分边界污染物物理排放强度":0.020000000,"分边界污染物物理排放强度单位":"吨/人"},
{"年份":2021,"企业名称":"尖沙咀置业集团有限公司","边界":"建筑工地","污染物来源":null,"原始污染物名称":"无害废物弃置强度","污染物":"无害废弃物","分边界污染物物理排放强度":0.070000000,"分边界污染物物理排放强度单位":"吨/平方米"},
{"年份":2021,"企业名称":"尖沙咀置业集团有限公司","边界":"酒店","污染物来源":null,"原始污染物名称":"无害废物弃置强度","污染物":"无害废弃物","分边界污染物物理排放强度":0.010000000,"分边界污染物物理排放强度单位":"吨/住客晚数"},
{"年份":2021,"企业名称":"尖沙咀置业集团有限公司","边界":"总部","污染物来源":null,"原始污染物名称":"有害废物弃置强度","污染物":"有害废弃物","分边界污染物物理排放强度":0.080000000,"分边界污染物物理排放强度单位":"公斤/人"},
{"年份":2021,"企业名称":"尖沙咀置业集团有限公司","边界":"物业管理","污染物来源":null,"原始污染物名称":"有害废物弃置强度","污染物":"有害废弃物","分边界污染物物理排放强度":0.001000000,"分边界污染物物理排放强度单位":"公斤/平方米"},
{"年份":2021,"企业名称":"信和置业有限公司","边界":"总部","污染物来源":null,"原始污染物名称":"无害废物弃置强度","污染物":"无害废弃物","分边界污染物物理排放强度":0.020000000,"分边界污染物物理排放强度单位":"吨/人"},
{"年份":2021,"企业名称":"信和置业有限公司","边界":"建筑工地","污染物来源":null,"原始污染物名称":"无害废物弃置强度","污染物":"无害废弃物","分边界污染物物理排放强度":0.070000000,"分边界污染物物理排放强度单位":"吨/平方米"},
{"年份":2021,"企业名称":"信和置业有限公司","边界":"酒店","污染物来源":null,"原始污染物名称":"无害废物弃置强度","污染物":"无害废弃物","分边界污染物物理排放强度":0.010000000,"分边界污染物物理排放强度单位":"吨/住客晚数"},
{"年份":2021,"企业名称":"信和置业有限公司","边界":"总部","污染物来源":null,"原始污染物名称":"有害废物弃置强度","污染物":"有害废弃物","分边界污染物物理排放强度":0.080000000,"分边界污染物物理排放强度单位":"公斤/人"},
{"年份":2021,"企业名称":"信和置业有限公司","边界":"物业管理","污染物来源":null,"原始污染物名称":"有害废物弃置强度","污染物":"有害废弃物","分边界污染物物理排放强度":0.001000000,"分边界污染物物理排放强度单位":"公斤/平方米"},
{"年份":2021,"企业名称":"阳光100中国控股有限公司","边界":"办公室","污染物来源":null,"原始污染物名称":"每名员工丢弃的有害废弃物","污染物":"有害废弃物","分边界污染物物理排放强度":1.450000000,"分边界污染物物理排放强度单位":"公斤/人"},
{"年份":2021,"企业名称":"阳光100中国控股有限公司","边界":"办公室","污染物来源":null,"原始污染物名称":"每名员工丢弃的无害废弃物","污染物":"无害废弃物","分边界污染物物理排放强度":46.520000000,"分边界污染物物理排放强度单位":"公斤/人"},
{"年份":2021,"企业名称":"金山软件有限公司","边界":"办公楼","污染物来源":null,"原始污染物名称":"人均有害废弃物","污染物":"有害废弃物","分边界污染物物理排放强度":0.000100000,"分边界污染物物理排放强度单位":"吨/人"},
{"年份":2021,"企业名称":"金山软件有限公司","边界":"办公楼","污染物来源":null,"原始污染物名称":"人均无害废弃物","污染物":"无害废弃物","分边界污染物物理排放强度":0.090000000,"分边界污染物物理排放强度单位":"吨/人"},
{"年份":2021,"企业名称":"丽新制衣国际有限公司","边界":"香港物业投资","污染物来源":null,"原始污染物名称":"已处理有害废弃物密度","污染物":"有害废弃物","分边界污染物物理排放强度":0.002400000,"分边界污染物物理排放强度单位":"千克/平方米"},
{"年份":2021,"企业名称":"丽新制衣国际有限公司","边界":"香港物业投资","污染物来源":null,"原始污染物名称":"所产生无害废弃物密度","污染物":"无害废弃物","分边界污染物物理排放强度":32.840000000,"分边界污染物物理排放强度单位":"千克/平方米"},
{"年份":2021,"企业名称":"丽新制衣国际有限公司","边界":"香港物业发展","污染物来源":null,"原始污染物名称":"所产生无害废弃物整体密度","污染物":"无害废弃物","分边界污染物物理排放强度":606.710000000,"分边界污染物物理排放强度单位":"千克/平方米"},
{"年份":2021,"企业名称":"丽新制衣国际有限公司","边界":"中国物业投资","污染物来源":null,"原始污染物名称":"已处理有害废弃物密度","污染物":"有害废弃物","分边界污染物物理排放强度":0.000800000,"分边界污染物物理排放强度单位":"千克/平方米"},
{"年份":2021,"企业名称":"丽新制衣国际有限公司","边界":"中国物业投资","污染物来源":null,"原始污染物名称":"所产生无害废弃物密度","污染物":"无害废弃物","分边界污染物物理排放强度":14.890000000,"分边界污染物物理排放强度单位":"千克/平方米"},
{"年份":2021,"企业名称":"丽新制衣国际有限公司","边界":"中国物业发展","污染物来源":null,"原始污染物名称":"已处理有害废弃物密度","污染物":"有害废弃物","分边界污染物物理排放强度":1.040000000,"分边界污染物物理排放强度单位":"千克/平方米"},
{"年份":2021,"企业名称":"丽新制衣国际有限公司","边界":"中国物业发展","污染物来源":null,"原始污染物名称":"所产生无害废弃物整体密度","污染物":"无害废弃物","分边界污染物物理排放强度":1.350000000,"分边界污染物物理排放强度单位":"千克/平方米"},
{"年份":2021,"企业名称":"丽新制衣国际有限公司","边界":"酒店","污染物来源":null,"原始污染物名称":"已处理有害废弃物整体密度","污染物":"有害废弃物","分边界污染物物理排放强度":0.004000000,"分边界污染物物理排放强度单位":"千克/平方米"},
{"年份":2021,"企业名称":"丽新制衣国际有限公司","边界":"酒店","污染物来源":null,"原始污染物名称":"所产生无害废弃物整体密度","污染物":"无害废弃物","分边界污染物物理排放强度":3.200000000,"分边界污染物物理排放强度单位":"千克/平方米"},
{"年份":2021,"企业名称":"丽新制衣国际有限公司","边界":"戏院","污染物来源":null,"原始污染物名称":"已处理有害废弃物整体密度","污染物":"有害废弃物","分边界污染物物理排放强度":0.004400000,"分边界污染物物理排放强度单位":"千克/平方米"},
{"年份":2021,"企业名称":"丽新制衣国际有限公司","边界":"戏院","污染物来源":null,"原始污染物名称":"已处理无害废弃物整体密度","污染物":"无害废弃物","分边界污染物物理排放强度":1.060000000,"分边界污染物物理排放强度单位":"千克/平方米"},
{"年份":2021,"企业名称":"丽新制衣国际有限公司","边界":"娱乐","污染物来源":null,"原始污染物名称":"所产生无害废弃物整体密度","污染物":"无害废弃物","分边界污染物物理排放强度":1.210000000,"分边界污染物物理排放强度单位":"千克/平方米"},
{"年份":2021,"企业名称":"丽新发展有限公司","边界":"香港物业投资","污染物来源":null,"原始污染物名称":"已处理有害废弃物密度","污染物":"有害废弃物","分边界污染物物理排放强度":0.002600000,"分边界污染物物理排放强度单位":"千克/平方米"},
{"年份":2021,"企业名称":"丽新发展有限公司","边界":"香港物业投资","污染物来源":null,"原始污染物名称":"所产生无害废弃物密度","污染物":"无害废弃物","分边界污染物物理排放强度":39.870000000,"分边界污染物物理排放强度单位":"千克/平方米"},
{"年份":2021,"企业名称":"丽新发展有限公司","边界":"香港物业发展","污染物来源":null,"原始污染物名称":"所产生无害废弃物整体密度","污染物":"无害废弃物","分边界污染物物理排放强度":606.710000000,"分边界污染物物理排放强度单位":"千克/平方米"},
{"年份":2021,"企业名称":"丽新发展有限公司","边界":"中国物业投资","污染物来源":null,"原始污染物名称":"已处理有害废弃物密度","污染物":"有害废弃物","分边界污染物物理排放强度":0.000800000,"分边界污染物物理排放强度单位":"千克/平方米"},
{"年份":2021,"企业名称":"丽新发展有限公司","边界":"中国物业投资","污染物来源":null,"原始污染物名称":"所产生无害废弃物密度","污染物":"无害废弃物","分边界污染物物理排放强度":14.890000000,"分边界污染物物理排放强度单位":"千克/平方米"},
{"年份":2021,"企业名称":"丽新发展有限公司","边界":"中国物业发展","污染物来源":null,"原始污染物名称":"已处理有害废弃物密度","污染物":"有害废弃物","分边界污染物物理排放强度":1.040000000,"分边界污染物物理排放强度单位":"千克/平方米"},
{"年份":2021,"企业名称":"丽新发展有限公司","边界":"中国物业发展","污染物来源":null,"原始污染物名称":"所产生无害废弃物整体密度","污染物":"无害废弃物","分边界污染物物理排放强度":1.350000000,"分边界污染物物理排放强度单位":"千克/平方米"},
{"年份":2021,"企业名称":"丽新发展有限公司","边界":"酒店","污染物来源":null,"原始污染物名称":"已处理有害废弃物整体密度","污染物":"有害废弃物","分边界污染物物理排放强度":0.004000000,"分边界污染物物理排放强度单位":"千克/平方米"},
{"年份":2021,"企业名称":"丽新发展有限公司","边界":"酒店","污染物来源":null,"原始污染物名称":"所产生无害废弃物整体密度","污染物":"无害废弃物","分边界污染物物理排放强度":3.200000000,"分边界污染物物理排放强度单位":"千克/平方米"},
{"年份":2021,"企业名称":"丽新发展有限公司","边界":"戏院","污染物来源":null,"原始污染物名称":"已处理有害废弃物整体密度","污染物":"有害废弃物","分边界污染物物理排放强度":0.004400000,"分边界污染物物理排放强度单位":"千克/平方米"},
{"年份":2021,"企业名称":"丽新发展有限公司","边界":"戏院","污染物来源":null,"原始污染物名称":"已处理无害废弃物整体密度","污染物":"无害废弃物","分边界污染物物理排放强度":1.060000000,"分边界污染物物理排放强度单位":"千克/平方米"},
{"年份":2021,"企业名称":"丽新发展有限公司","边界":"娱乐","污染物来源":null,"原始污染物名称":"所产生无害废弃物整体密度","污染物":"无害废弃物","分边界污染物物理排放强度":1.210000000,"分边界污染物物理排放强度单位":"千克/平方米"},
{"年份":2021,"企业名称":"三巽控股集团有限公司","边界":"办公室","污染物来源":null,"原始污染物名称":"无害废弃物密度","污染物":"无害废弃物","分边界污染物物理排放强度":0.130000000,"分边界污染物物理排放强度单位":"吨/人"},
{"年份":2021,"企业名称":"三巽控股集团有限公司","边界":"办公室","污染物来源":null,"原始污染物名称":"有害废弃物密度","污染物":"有害废弃物","分边界污染物物理排放强度":0.430000000,"分边界污染物物理排放强度单位":"千克/人"},
{"年份":2021,"企业名称":"中手游科技集团有限公司","边界":"办公室","污染物来源":null,"原始污染物名称":"无害废物","污染物":"无害废弃物","分边界污染物物理排放强度":0.070000000,"分边界污染物物理排放强度单位":"吨/人"},
{"年份":2021,"企业名称":"伟能集团国际控股有限公司","边界":"办公室","污染物来源":null,"原始污染物名称":"无害废弃物","污染物":"无害废弃物","分边界污染物物理排放强度":1.160000000,"分边界污染物物理排放强度单位":"公斤/百万楼面面积"},
{"年份":2021,"企业名称":"伟能集团国际控股有限公司","边界":"IBO项目","污染物来源":null,"原始污染物名称":"无害废弃物","污染物":"无害废弃物","分边界污染物物理排放强度":0.000020000,"分边界污染物物理排放强度单位":"公斤/千瓦时发电量"},
{"年份":2021,"企业名称":"伟能集团国际控股有限公司","边界":"IBO项目","污染物来源":null,"原始污染物名称":"有害废弃物","污染物":"有害废弃物","分边界污染物物理排放强度":0.000200000,"分边界污染物物理排放强度单位":"公斤/千瓦时发电量"},
{"年份":2021,"企业名称":"笔克远东集团有限公司","边界":"生产厂房","污染物来源":null,"原始污染物名称":"每楼面面积所产生有害废弃物总量","污染物":"有害废弃物","分边界污染物物理排放强度":0.150000000,"分边界污染物物理排放强度单位":"千克/平方米"},
{"年份":2021,"企业名称":"甘肃银行股份有限公司","边界":"办公室","污染物来源":null,"原始污染物名称":"废弃办公室废物产生密度","污染物":"无害废弃物","分边界污染物物理排放强度":0.280000000,"分边界污染物物理排放强度单位":"千克/平方米"},
{"年份":2021,"企业名称":"汇聚科技有限公司","边界":"数字电线业务分部","污染物来源":null,"原始污染物名称":"有害废弃物密度","污染物":"有害废弃物","分边界污染物物理排放强度":0.010000000,"分边界污染物物理排放强度单位":"公斤/每公里"},
{"年份":2021,"企业名称":"汇聚科技有限公司","边界":"电线组件业务分部及总部","污染物来源":null,"原始污染物名称":"有害废弃物密度","污染物":"有害废弃物","分边界污染物物理排放强度":2.050000000,"分边界污染物物理排放强度单位":"公斤/人"},
{"年份":2021,"企业名称":"汇聚科技有限公司","边界":"数字电线业务分部","污染物来源":null,"原始污染物名称":"无害废弃物密度","污染物":"无害废弃物","分边界污染物物理排放强度":1.590000000,"分边界污染物物理排放强度单位":"公斤/每公里"},
{"年份":2021,"企业名称":"汇聚科技有限公司","边界":"电线组件业务分部及总部","污染物来源":null,"原始污染物名称":"无害废弃物密度","污染物":"无害废弃物","分边界污染物物理排放强度":71.820000000,"分边界污染物物理排放强度单位":"公斤/人"},
{"年份":2021,"企业名称":"阳光电源股份有限公司","边界":"阳光电源及成员企业","污染物来源":null,"原始污染物名称":"单位产品危险废物量","污染物":"有害废弃物","分边界污染物物理排放强度":0.680000000,"分边界污染物物理排放强度单位":"千克/兆瓦"},
{"年份":2021,"企业名称":"阳光电源股份有限公司","边界":"阳光电源及成员企业","污染物来源":null,"原始污染物名称":"单位产品颗粒物排放","污染物":"颗粒物","分边界污染物物理排放强度":0.100000000,"分边界污染物物理排放强度单位":"千克/兆瓦"},
{"年份":2021,"企业名称":"阳光电源股份有限公司","边界":"阳光电源及成员企业","污染物来源":null,"原始污染物名称":"单位产品非甲烷总烃排放","污染物":"其他","分边界污染物物理排放强度":0.060000000,"分边界污染物物理排放强度单位":"千克/兆瓦"},
{"年份":2021,"企业名称":"阳光电源股份有限公司","边界":"阳光电源及成员企业","污染物来源":null,"原始污染物名称":"单位产品氨氮排放","污染物":"氨氮","分边界污染物物理排放强度":0.050000000,"分边界污染物物理排放强度单位":"千克/兆瓦"},
{"年份":2021,"企业名称":"阳光电源股份有限公司","边界":"阳光电源及成员企业","污染物来源":null,"原始污染物名称":"单位产品COD排放","污染物":"化学需氧量(COD)","分边界污染物物理排放强度":0.510000000,"分边界污染物物理排放强度单位":"千克/兆瓦"},
{"年份":2021,"企业名称":"广州富力地产股份有限公司","边界":"商业管理","污染物来源":null,"原始污染物名称":"危险废弃物产生密度","污染物":"有害废弃物","分边界污染物物理排放强度":0.000010000,"分边界污染物物理排放强度单位":"吨/平方米"},
{"年份":2021,"企业名称":"广州富力地产股份有限公司","边界":"酒店","污染物来源":null,"原始污染物名称":"危险废弃物产生密度","污染物":"有害废弃物","分边界污染物物理排放强度":0.011000000,"分边界污染物物理排放强度单位":"吨/平方米"},
{"年份":2021,"企业名称":"广州富力地产股份有限公司","边界":"商业管理","污染物来源":null,"原始污染物名称":"无害废弃物产生密度","污染物":"无害废弃物","分边界污染物物理排放强度":0.008000000,"分边界污染物物理排放强度单位":"吨/平方米"},
{"年份":2021,"企业名称":"广州富力地产股份有限公司","边界":"酒店","污染物来源":null,"原始污染物名称":"无害废弃物产生密度","污染物":"无害废弃物","分边界污染物物理排放强度":0.163000000,"分边界污染物物理排放强度单位":"吨/平方米"},
{"年份":2021,"企业名称":"广州富力地产股份有限公司","边界":"办公场所","污染物来源":null,"原始污染物名称":"无害废弃物产生密度","污染物":"无害废弃物","分边界污染物物理排放强度":0.039000000,"分边界污染物物理排放强度单位":"吨/平方米"},
{"年份":2021,"企业名称":"广州富力地产股份有限公司","边界":"在建项目","污染物来源":null,"原始污染物名称":"无害废弃物产生密度","污染物":"无害废弃物","分边界污染物物理排放强度":0.020000000,"分边界污染物物理排放强度单位":"吨/平方米"},
{"年份":2021,"企业名称":"广州富力地产股份有限公司","边界":"办公场所","污染物来源":null,"原始污染物名称":"硫氧化物(SOx)","污染物":"二氧化硫","分边界污染物物理排放强度":0.031000000,"分边界污染物物理排放强度单位":"吨/平方米"},
{"年份":2021,"企业名称":"广州富力地产股份有限公司","边界":"在建项目","污染物来源":null,"原始污染物名称":"硫氧化物(SOx)","污染物":"二氧化硫","分边界污染物物理排放强度":0.026000000,"分边界污染物物理排放强度单位":"吨/平方米"},
{"年份":2021,"企业名称":"广州富力地产股份有限公司","边界":"办公场所","污染物来源":null,"原始污染物名称":"氮氧化物(NOx)","污染物":"氮氧化物","分边界污染物物理排放强度":5.451000000,"分边界污染物物理排放强度单位":"吨/平方米"},
{"年份":2021,"企业名称":"广州富力地产股份有限公司","边界":"在建项目","污染物来源":null,"原始污染物名称":"氮氧化物(NOx)","污染物":"氮氧化物","分边界污染物物理排放强度":1.335000000,"分边界污染物物理排放强度单位":"吨/平方米"},
{"年份":2021,"企业名称":null,"边界":null,"污染物来源":null,"原始污染物名称":"无害废弃物产生密度","污染物":"无害废弃物","分边界污染物物理排放强度":0.390000000,"分边界污染物物理排放强度单位":"吨/台"},
{"年份":2021,"企业名称":null,"边界":null,"污染物来源":null,"原始污染物名称":"危险废弃物产生密度","污染物":"有害废弃物","分边界污染物物理排放强度":0.020000000,"分边界污染物物理排放强度单位":"吨/台"},
{"年份":2021,"企业名称":null,"边界":null,"污染物来源":null,"原始污染物名称":"无害废弃物产生密度","污染物":"无害废弃物","分边界污染物物理排放强度":90.670000000,"分边界污染物物理排放强度单位":"吨/千吨生产量"},
{"年份":2021,"企业名称":null,"边界":null,"污染物来源":null,"原始污染物名称":"危险废弃物产生密度","污染物":"有害废弃物","分边界污染物物理排放强度":0.080000000,"分边界污染物物理排放强度单位":"吨/千吨生产量"}
]}